chess_insight/__init__.py
chess_insight/api_communicator.py
chess_insight/chess_com_api_communicator.py
chess_insight/game.py
chess_insight/lichess_api_communicator.py
chess_insight/main.py
chess_insight/player.py
chess_insight/semi_dataclass.py
chess_insight/utils.py
chess_insight/data/openings.json
chess_insight-0.9.2.dist-info/METADATA
chess_insight-0.9.2.dist-info/WHEEL
chess_insight-0.9.2.dist-info/top_level.txt
chess_insight-0.9.2.dist-info/RECORD
